desec_dnsupdater/desec_dyndns.py
desec_dnsupdater-0.1.4.dist-info/LICENSE
desec_dnsupdater-0.1.4.dist-info/METADATA
desec_dnsupdater-0.1.4.dist-info/WHEEL
desec_dnsupdater-0.1.4.dist-info/entry_points.txt
desec_dnsupdater-0.1.4.dist-info/RECORD
