Metadata-Version: 2.3
Name: desec-dnsupdater
Version: 0.1.4
Summary: A simple DynDNS client for deSEC.io
License: MIT
Author: Ole Langbehn
Author-email: ole@langbehn.family
Requires-Python: >=3.11,<3.14
Classifier: Development Status :: 2 - Pre-Alpha
Classifier: Environment :: Console
Classifier: Intended Audience :: System Administrators
Classifier: License :: OSI Approved :: MIT License
Classifier: Operating System :: OS Independent
Classifier: Programming Language :: Python :: 3
Classifier: Programming Language :: Python :: 3.11
Classifier: Programming Language :: Python :: 3.12
Classifier: Programming Language :: Python :: 3.13
Classifier: Topic :: System :: Networking
Classifier: Typing :: Typed
Requires-Dist: click (>=8.1.8)
Requires-Dist: desec-dns (>=1.2.0)
Requires-Dist: dnspython (>=2.7.0)
Requires-Dist: ifaddr (>=0.2.0)
Requires-Dist: netifaces2 (>=0.0.22)
Project-URL: Repository, https://github.com/neurolabs/desec-dnsupdater
Project-URL: issues, https://github.com/neurolabs/desec-dnsupdater/issues
